contributter_ranking_bot/__init__.py
contributter_ranking_bot/contributter_ranking.py
contributter_ranking_bot/main.py
contributter_ranking_bot-0.1.2.dist-info/LICENSE
contributter_ranking_bot-0.1.2.dist-info/METADATA
contributter_ranking_bot-0.1.2.dist-info/WHEEL
contributter_ranking_bot-0.1.2.dist-info/entry_points.txt
contributter_ranking_bot-0.1.2.dist-info/top_level.txt
contributter_ranking_bot-0.1.2.dist-info/RECORD
