Metadata-Version: 2.1
Name: contributter-ranking-bot
Version: 0.1.2
Summary: Contributter Ranking Bot
Home-page: https://github.com/eggplants/contributter-ranking-bot
Author: HARUTA (shuntatakemoto)
Author-email: rt80405@gmail.com
Maintainer: eggplants
Maintainer-email: w10776e8w@yahoo.co.jp
License: MIT
Platform: UNKNOWN
Classifier: Development Status :: 3 - Alpha
Classifier: Environment :: Console
Classifier: Environment :: Web Environment
Classifier: License :: OSI Approved :: MIT License
Classifier: Programming Language :: Python :: 3
Classifier: Programming Language :: Python :: 3 :: Only
Classifier: Programming Language :: Python :: 3.7
Classifier: Programming Language :: Python :: 3.8
Classifier: Programming Language :: Python :: 3.9
Classifier: Programming Language :: Python :: 3.10
Classifier: Typing :: Typed
Requires-Python: >=3.7
License-File: LICENSE
Requires-Dist: python-dotenv
Requires-Dist: requests-oauthlib
Provides-Extra: all
Requires-Dist: black ; extra == 'all'
Requires-Dist: flake8 ; extra == 'all'
Requires-Dist: isort ; extra == 'all'
Requires-Dist: mypy ; extra == 'all'
Requires-Dist: pre-commit ; extra == 'all'
Requires-Dist: pylint ; extra == 'all'
Requires-Dist: setuptools (>=46.4.0) ; extra == 'all'
Requires-Dist: types-setuptools ; extra == 'all'
Provides-Extra: dev
Requires-Dist: black ; extra == 'dev'
Requires-Dist: flake8 ; extra == 'dev'
Requires-Dist: isort ; extra == 'dev'
Requires-Dist: mypy ; extra == 'dev'
Requires-Dist: pre-commit ; extra == 'dev'
Requires-Dist: pylint ; extra == 'dev'
Requires-Dist: setuptools (>=46.4.0) ; extra == 'dev'
Provides-Extra: types
Requires-Dist: types-setuptools ; extra == 'types'
